pysabr/__init__.py
pysabr/black.py
pysabr/helpers.py
pysabr/models/__init__.py
pysabr/models/base_sabr.py
pysabr/models/hagan_2002_lognormal_sabr.py
pysabr/models/hagan_2002_normal_sabr.py
pysabr/models/hagan_2013_normal_sabr.py
pysabr-0.4.1.dist-info/LICENSE
pysabr-0.4.1.dist-info/METADATA
pysabr-0.4.1.dist-info/WHEEL
pysabr-0.4.1.dist-info/top_level.txt
pysabr-0.4.1.dist-info/RECORD
